rarbg.py
rarbg-1.2.2.dist-info/entry_points.txt
rarbg-1.2.2.dist-info/WHEEL
rarbg-1.2.2.dist-info/METADATA
rarbg-1.2.2.dist-info/RECORD
