Metadata-Version: 2.1
Name: rarbg
Version: 1.2.2
Summary: RSS interface to TorrentAPI
Home-page: https://github.com/banteg/rarbg
Author: banteg
Author-email: banteeg@gmail.com
Requires-Python: >=3.6,<4.0
Classifier: Programming Language :: Python :: 3
Classifier: Programming Language :: Python :: 3.6
Classifier: Programming Language :: Python :: 3.7
Requires-Dist: aiohttp (>=3.5,<4.0)
Requires-Dist: click (>=7.0,<8.0)
Requires-Dist: humanize (>=0.5.1,<0.6.0)
Requires-Dist: jinja2 (>=2.10,<3.0)
Requires-Dist: python-dateutil (>=2.8,<3.0)
Project-URL: Repository, https://github.com/banteg/rarbg
